setup.cfg
setup.py
FuncDesigner/BooleanOOFun.py
FuncDesigner/FDmisc.py
FuncDesigner/Interval.py
FuncDesigner/__init__.py
FuncDesigner/baseClasses.py
FuncDesigner/boundsurf.py
FuncDesigner/boundsurf2.py
FuncDesigner/categorical.py
FuncDesigner/constraints.py
FuncDesigner/constraints2.py
FuncDesigner/constraints3.py
FuncDesigner/dae.py
FuncDesigner/debugMisc.py
FuncDesigner/derivativeMisc.py
FuncDesigner/distribution.py
FuncDesigner/expression.py
FuncDesigner/integrate.py
FuncDesigner/interpolate.py
FuncDesigner/iqg.py
FuncDesigner/iqg2.py
FuncDesigner/logic.py
FuncDesigner/multiarray.py
FuncDesigner/ode.py
FuncDesigner/ooFun.py
FuncDesigner/ooPoint.py
FuncDesigner/ooSystem.py
FuncDesigner/ooVar.py
FuncDesigner/ooarray.py
FuncDesigner/overloads.py
FuncDesigner/sle.py
FuncDesigner/stencils.py
FuncDesigner/translator.py
FuncDesigner.egg-info/PKG-INFO
FuncDesigner.egg-info/SOURCES.txt
FuncDesigner.egg-info/dependency_links.txt
FuncDesigner.egg-info/not-zip-safe
FuncDesigner.egg-info/requires.txt
FuncDesigner.egg-info/top_level.txt
FuncDesigner/examples/OptWithFixedVars.py
FuncDesigner/examples/PythonFuncs.py
FuncDesigner/examples/__init__.py
FuncDesigner/examples/categoricalVars.py
FuncDesigner/examples/cycle_for.py
FuncDesigner/examples/eig1.py
FuncDesigner/examples/eig2.py
FuncDesigner/examples/equation.py
FuncDesigner/examples/exactGlobalMINLP.py
FuncDesigner/examples/exactGlobalMOP.py
FuncDesigner/examples/exactGlobalNLP.py
FuncDesigner/examples/exactODE.py
FuncDesigner/examples/expressions.py
FuncDesigner/examples/getDerivs.py
FuncDesigner/examples/glp1.py
FuncDesigner/examples/ifThenElse.py
FuncDesigner/examples/integrate1.py
FuncDesigner/examples/integrate2.py
FuncDesigner/examples/integrate3.py
FuncDesigner/examples/integrator.py
FuncDesigner/examples/interalg100vars.py
FuncDesigner/examples/interp1.py
FuncDesigner/examples/interval1.py
FuncDesigner/examples/llsp1.py
FuncDesigner/examples/lp1.py
FuncDesigner/examples/lp2.py
FuncDesigner/examples/lp3.py
FuncDesigner/examples/milp1.py
FuncDesigner/examples/minlp1.py
FuncDesigner/examples/miqcqp1.py
FuncDesigner/examples/mop1.py
FuncDesigner/examples/mop3.py
FuncDesigner/examples/nlp1.py
FuncDesigner/examples/nlpSparse.py
