Metadata-Version: 1.2
Name: FuncDesigner
Version: 0.5629
Summary: A python module for function design and automatic derivatives
Home-page: http://openopt.org
Maintainer: Dmitrey Kroshko
Maintainer-email: dmitrey@openopt.org
License: BSD
Platform: UNKNOWN
Classifier: Development Status :: 5 - Production/Stable
Classifier: Environment :: Console
Classifier: Intended Audience :: Developers
Classifier: Intended Audience :: Science/Research
Classifier: License :: OSI Approved :: BSD License
Classifier: Topic :: Scientific/Engineering
